{
  "id": "syncwave-local-env",
  "name": "SyncWave \u2014 Local",
  "values": [
    {
      "key": "baseUrl",
      "value": "http://localhost:5000/api/v1",
      "enabled": true
    },
    {
      "key": "accessToken",
      "value": "",
      "enabled": true
    },
    {
      "key": "refreshToken",
      "value": "",
      "enabled": true
    },
    {
      "key": "userId",
      "value": "",
      "enabled": true
    },
    {
      "key": "roomId",
      "value": "",
      "enabled": true
    },
    {
      "key": "songId",
      "value": "",
      "enabled": true
    },
    {
      "key": "artistId",
      "value": "",
      "enabled": true
    },
    {
      "key": "albumId",
      "value": "",
      "enabled": true
    },
    {
      "key": "playlistId",
      "value": "",
      "enabled": true
    },
    {
      "key": "voteId",
      "value": "",
      "enabled": true
    },
    {
      "key": "messageId",
      "value": "",
      "enabled": true
    },
    {
      "key": "requestId",
      "value": "",
      "enabled": true
    },
    {
      "key": "notificationId",
      "value": "",
      "enabled": true
    },
    {
      "key": "reportId",
      "value": "",
      "enabled": true
    },
    {
      "key": "conversationId",
      "value": "",
      "enabled": true
    }
  ]
}